[
    {
      "id": 1,
      "tecnumber": 3143,
      "customerId": 1,
      "customerlabel": "Ionautics",
      "dateorderreceived": "2020-10-21",
      "quantity": 1,
      "reference": "SR700V-300W",
      "devisnumber": "d20-0293",
      "deliverydateplanned": "2020-12-21",
      "status": "Valide",
      "observation": ""
    },
    {
        "id": 2,
        "tecnumber": 3153,
        "customerId": 1,
        "customerlabel": "Ionautics 2",
        "dateorderreceived": "2020-10-30",
        "quantity": 2,
        "reference": "SR400V-300W",
        "devisnumber": "d20-0292",
        "deliverydateplanned": "2020-12-21",
        "status": "Valide",
        "observation": ""
    },
    {
        "id": 3,
        "tecnumber": 3243,
        "customerId": 1,
        "customerlabel": "Ionau",
        "dateorderreceived": "2020-11-01",
        "quantity": 3,
        "reference": "SR300V-200W",
        "devisnumber": "d21-0292",
        "deliverydateplanned": "2020-12-21",
        "status": "En cours",
        "observation": ""
    },
    {
        "id": 4,
        "tecnumber": 3443,
        "customerId": 1,
        "customerlabel": "EdF",
        "dateorderreceived": "2020-11-05",
        "quantity": 1,
        "reference": "SR700V-150W",
        "devisnumber": "d20-0392",
        "deliverydateplanned": "2020-12-21",
        "status": "A valider",
        "observation": ""
    },
    {
        "id": 5,
        "tecnumber": 3643,
        "customerId": 1,
        "customerlabel": "Meto",
        "dateorderreceived": "2020-11-07",
        "quantity": 1,
        "reference": "SR400V-500W",
        "devisnumber": "d20-0202",
        "deliverydateplanned": "2020-12-21",
        "status": "En cours",
        "observation": ""
    },
    {
        "id": 6,
        "tecnumber": 3743,
        "customerId": 1,
        "customerlabel": "cdef",
        "dateorderreceived": "2020-11-10",
        "quantity": 5,
        "reference": "SR700V-300W",
        "devisnumber": "d60-0292",
        "deliverydateplanned": "2020-12-21",
        "status": "Valide",
        "observation": ""
    },
    {
        "id": 7,
        "tecnumber": 3542,
        "customerId": 1,
        "customerlabel": "dkllld",
        "dateorderreceived": "2020-11-07",
        "quantity": 1,
        "reference": "SR700V-600W",
        "devisnumber": "d25-0292",
        "deliverydateplanned": "2020-12-21",
        "status": "En cours",
        "observation": ""
    }
]
  